hwdean.py
hwdean-0.0.7.dist-info/LICENSE.txt
hwdean-0.0.7.dist-info/METADATA
hwdean-0.0.7.dist-info/WHEEL
hwdean-0.0.7.dist-info/top_level.txt
hwdean-0.0.7.dist-info/RECORD
