Metadata-Version: 2.1
Name: hwdean
Version: 0.0.7
Summary: A package for training and predicting temporal cell
Home-page: https://bitbucket.astrazeneca.com/users/krjm801/repos/package_dev
Author: Dean Sumner
Author-email: dean.sumner@astrazeneca.net
License: MIT
Download-URL: https://bitbucket.astrazeneca.com/users/krjm801/repos/package_dev/browse/dist/hwdean-0.0.7.tar.gz
Platform: UNKNOWN
Classifier: Programming Language :: Python :: 3.8
Classifier: License :: OSI Approved :: MIT License
Classifier: Operating System :: OS Independent
